preload/__init__.py
preload/preload.py
preload-2.2.dist-info/LICENSE
preload-2.2.dist-info/METADATA
preload-2.2.dist-info/WHEEL
preload-2.2.dist-info/top_level.txt
preload-2.2.dist-info/RECORD
