Metadata-Version: 2.1
Name: preload
Version: 2.2
Summary: Give user feedback while importing heavy modules
Home-page: https://github.com/tfiers/preload
Author: Tomas Fiers
Author-email: tomas.fiers@gmail.com
License: UNKNOWN
Project-URL: Source Code, https://github.com/tfiers/preload
Platform: UNKNOWN
Classifier: License :: OSI Approved :: MIT License
Classifier: Programming Language :: Python :: 3
Classifier: Operating System :: OS Independent
